.travis.yml
AUTHORS
CHANGES
LICENSE
MANIFEST.in
Makefile
README.rst
conftest.py
runtests.py
setup.cfg
setup.py
tox.ini
docs/Makefile
docs/conf.py
docs/index.rst
docs/make.bat
docs/usage.rst
docs/changelog/index.rst
docs/config/celery.rst
docs/config/django.rst
docs/config/flask.rst
docs/config/index.rst
docs/config/logbook.rst
docs/config/logging.rst
docs/config/pylons.rst
docs/config/pyramid.rst
docs/config/tornado.rst
docs/config/wsgi.rst
docs/config/zerorpc.rst
docs/config/zope.rst
docs/contributing/index.rst
docs/install/index.rst
mr.poe.egg-info/PKG-INFO
mr.poe.egg-info/SOURCES.txt
mr.poe.egg-info/dependency_links.txt
mr.poe.egg-info/entry_points.txt
mr.poe.egg-info/not-zip-safe
mr.poe.egg-info/requires.txt
mr.poe.egg-info/top_level.txt
raven/__init__.py
raven/base.py
raven/context.py
raven/events.py
raven/middleware.py
raven/processors.py
raven/conf/__init__.py
raven/conf/defaults.py
raven/contrib/__init__.py
raven/contrib/async.py
raven/contrib/paste.py
raven/contrib/celery/__init__.py
raven/contrib/django/__init__.py
raven/contrib/django/client.py
raven/contrib/django/handlers.py
raven/contrib/django/logging.py
raven/contrib/django/models.py
raven/contrib/django/serializers.py
raven/contrib/django/urls.py
raven/contrib/django/utils.py
raven/contrib/django/views.py
raven/contrib/django/celery/__init__.py
raven/contrib/django/celery/models.py
raven/contrib/django/celery/tasks.py
raven/contrib/django/middleware/__init__.py
raven/contrib/django/middleware/wsgi.py
raven/contrib/django/raven_compat/__init__.py
raven/contrib/django/raven_compat/handlers.py
raven/contrib/django/raven_compat/models.py
raven/contrib/django/raven_compat/middleware/__init__.py
raven/contrib/django/raven_compat/middleware/wsgi.py
raven/contrib/django/raven_compat/templatetags/__init__.py
raven/contrib/django/raven_compat/templatetags/raven.py
raven/contrib/django/templatetags/__init__.py
raven/contrib/django/templatetags/raven.py
raven/contrib/flask/__init__.py
raven/contrib/flask/utils.py
raven/contrib/pylons/__init__.py
raven/contrib/tornado/__init__.py
raven/contrib/transports/__init__.py
raven/contrib/transports/zeromq/__init__.py
raven/contrib/transports/zeromq/raven_zmq.py
