Metadata-Version: 1.0
Name: mr.poe
Version: 3.1.16-3
Summary: mr.poe is a fork of raven-python for ancient versions of Python
Home-page: http://github.com/collective/mr.poe
Author: David Cramer
Author-email: dcramer@gmail.com
License: UNKNOWN
Platform: UNKNOWN
Classifier: Intended Audience :: Developers
Classifier: Intended Audience :: System Administrators
Classifier: Operating System :: OS Independent
Classifier: Topic :: Software Development
Classifier: Programming Language :: Python :: 2.4
Classifier: Framework :: Zope2
